Metadata-Version: 1.1
Name: dm.reuse
Version: 2.1.1
Summary: Support for object reuse with slight modifications
Home-page: https://pypi.org/project/dm.reuse
Author: Dieter Maurer
Author-email: dieter@handshake.de
License: BSD (see "dm/reuse/LICENSE.txt", for details)
Keywords: reuse
Platform: UNKNOWN
Classifier: Development Status :: 5 - Production/Stable
Classifier: Intended Audience :: Developers
Classifier: License :: OSI Approved :: BSD License
Classifier: Operating System :: OS Independent
Classifier: Programming Language :: Python
Classifier: Programming Language :: Python :: 2.7
Classifier: Programming Language :: Python :: 3
Classifier: Topic :: Software Development
Classifier: Topic :: Utilities
